pyutau/__init__.py
pyutau/pyutau.py
pyutau-1.3.0.dist-info/LICENSE.txt
pyutau-1.3.0.dist-info/METADATA
pyutau-1.3.0.dist-info/WHEEL
pyutau-1.3.0.dist-info/top_level.txt
pyutau-1.3.0.dist-info/RECORD
