Metadata-Version: 2.1
Name: pyutau
Version: 1.3.0
Summary: A python library/module for parsing UTAU plugin data
Home-page: https://github.com/UtaUtaUtau/pyUtau
Download-URL: https://github.com/UtaUtaUtau/pyUtau/archive/refs/tags/v1.3.0.tar.gz
Author: UtaUtaUtau
Author-email: diamond.glacier16@gmail.com
License: MIT
Keywords: utau
Classifier: Development Status :: 4 - Beta
Classifier: Intended Audience :: Developers
Classifier: License :: OSI Approved :: MIT License
Classifier: Operating System :: Microsoft :: Windows
Classifier: Programming Language :: Python :: 3
Classifier: Programming Language :: Python :: 3.10
License-File: LICENSE.txt
